{
  "project_info": {
    "project_number": "599910257056",
    "project_id": "chatapp-3f4df",
    "storage_bucket": "chatapp-3f4df.appspot.com"
  },
  "client": [
    {
      "client_info": {
        "mobilesdk_app_id": "1:599910257056:android:1d7517762b2b178c7494c5",
        "android_client_info": {
          "package_name": "com.example.flutter_application_1"
        }
      },
      "oauth_client": [],
      "api_key": [
        {
          "current_key": "AIzaSyB6AUA8ZSrbKQqCKZZ21ZzIbfSnC0UoI2s"
        }
      ],
      "services": {
        "appinvite_service": {
          "other_platform_oauth_client": []
        }
      }
    }
  ],
  "configuration_version": "1"
}